tumpacrypto/__init__.py
tumpacrypto/affirm.py
tumpacrypto/dilation.py
tumpacrypto/edge.py
tumpacrypto/glcm.py
tumpacrypto/houghtransform.py
tumpacrypto/isolated.py
tumpacrypto/region.py
tumpacrypto/rsads.py
tumpacrypto/sdes.py
tumpacrypto/watershed.py
tumpacrypto/watershedclahe.py
tumpacrypto-0.1.2.dist-info/licenses/LICENSE
tumpacrypto-0.1.2.dist-info/METADATA
tumpacrypto-0.1.2.dist-info/WHEEL
tumpacrypto-0.1.2.dist-info/top_level.txt
tumpacrypto-0.1.2.dist-info/RECORD
