Metadata-Version: 2.4
Name: tumpacrypto
Version: 0.1.2
Summary: Cryptography implementations
Author: Bombolcat
License: MIT
Classifier: License :: OSI Approved :: MIT License
Classifier: Programming Language :: Python :: 3
Requires-Python: >=3.8
License-File: LICENSE
Dynamic: license-file
